tidyversetopandas/__init__.py
tidyversetopandas/tidyversetopandas.py
tidyversetopandas-3.0.0.dist-info/LICENSE
tidyversetopandas-3.0.0.dist-info/METADATA
tidyversetopandas-3.0.0.dist-info/WHEEL
tidyversetopandas-3.0.0.dist-info/RECORD
