Metadata-Version: 2.1
Name: tidyversetopandas
Version: 3.0.0
Summary: Common tidyverse functions for pandas!
License: MIT
Author: Thomas, Sophia, Lily, Nando
Requires-Python: >=3.9,<4.0
Classifier: License :: OSI Approved :: MIT License
Classifier: Programming Language :: Python :: 3
Classifier: Programming Language :: Python :: 3.9
Classifier: Programming Language :: Python :: 3.10
Classifier: Programming Language :: Python :: 3.11
Classifier: Programming Language :: Python :: 3.12
Requires-Dist: pandas (>=2.1.4,<3.0.0)
Requires-Dist: pyarrow (>=15.0.0,<16.0.0)
